odoo/addons/stock_available_stock_mts_mto_rule/README.rst
odoo/addons/stock_available_stock_mts_mto_rule/__init__.py
odoo/addons/stock_available_stock_mts_mto_rule/__manifest__.py
odoo/addons/stock_available_stock_mts_mto_rule/i18n/it.po
odoo/addons/stock_available_stock_mts_mto_rule/i18n/stock_available_stock_mts_mto_rule.pot
odoo/addons/stock_available_stock_mts_mto_rule/models/__init__.py
odoo/addons/stock_available_stock_mts_mto_rule/models/stock_rule.py
odoo/addons/stock_available_stock_mts_mto_rule/readme/CONTRIBUTORS.rst
odoo/addons/stock_available_stock_mts_mto_rule/readme/DESCRIPTION.rst
odoo/addons/stock_available_stock_mts_mto_rule/static/description/icon.png
odoo/addons/stock_available_stock_mts_mto_rule/static/description/index.html
odoo14_addon_stock_available_stock_mts_mto_rule-14.0.1.0.1.dev5.dist-info/METADATA
odoo14_addon_stock_available_stock_mts_mto_rule-14.0.1.0.1.dev5.dist-info/WHEEL
odoo14_addon_stock_available_stock_mts_mto_rule-14.0.1.0.1.dev5.dist-info/top_level.txt
odoo14_addon_stock_available_stock_mts_mto_rule-14.0.1.0.1.dev5.dist-info/RECORD
