Metadata-Version: 2.1
Name: odoo14-addon-stock_available_stock_mts_mto_rule
Version: 14.0.1.0.1.dev5
Summary: Stock Avaiable Stock Mts Mto Rule
Home-page: https://github.com/OCA/stock-logistics-warehouse
Author: Camptocamp,Odoo Community Association (OCA)
Author-email: support@odoo-community.org
License: AGPL-3
Classifier: Programming Language :: Python
Classifier: Framework :: Odoo
Classifier: Framework :: Odoo :: 14.0
Classifier: License :: OSI Approved :: GNU Affero General Public License v3
Requires-Python: >=3.6
Requires-Dist: odoo14-addon-stock-available
Requires-Dist: odoo14-addon-stock-mts-mto-rule
Requires-Dist: odoo<14.1dev,>=14.0a
